pretix_stay22/__init__.py
pretix_stay22/apps.py
pretix_stay22/signals.py
pretix_stay22/urls.py
pretix_stay22/views.py
pretix_stay22/locale/django.pot
pretix_stay22/locale/ar/LC_MESSAGES/django.mo
pretix_stay22/locale/ar/LC_MESSAGES/django.po
pretix_stay22/locale/cs/LC_MESSAGES/django.mo
pretix_stay22/locale/cs/LC_MESSAGES/django.po
pretix_stay22/locale/da/LC_MESSAGES/django.mo
pretix_stay22/locale/da/LC_MESSAGES/django.po
pretix_stay22/locale/de/LC_MESSAGES/django.mo
pretix_stay22/locale/de/LC_MESSAGES/django.po
pretix_stay22/locale/de_Informal/.gitkeep
pretix_stay22/locale/de_Informal/LC_MESSAGES/django.mo
pretix_stay22/locale/de_Informal/LC_MESSAGES/django.po
pretix_stay22/locale/el/LC_MESSAGES/django.mo
pretix_stay22/locale/el/LC_MESSAGES/django.po
pretix_stay22/locale/es/LC_MESSAGES/django.mo
pretix_stay22/locale/es/LC_MESSAGES/django.po
pretix_stay22/locale/fi/LC_MESSAGES/django.mo
pretix_stay22/locale/fi/LC_MESSAGES/django.po
pretix_stay22/locale/fr/LC_MESSAGES/django.mo
pretix_stay22/locale/fr/LC_MESSAGES/django.po
pretix_stay22/locale/hr/LC_MESSAGES/django.mo
pretix_stay22/locale/hr/LC_MESSAGES/django.po
pretix_stay22/locale/lv/LC_MESSAGES/django.mo
pretix_stay22/locale/lv/LC_MESSAGES/django.po
pretix_stay22/locale/nl/LC_MESSAGES/django.mo
pretix_stay22/locale/nl/LC_MESSAGES/django.po
pretix_stay22/locale/nl_Informal/LC_MESSAGES/django.mo
pretix_stay22/locale/nl_Informal/LC_MESSAGES/django.po
pretix_stay22/locale/ru/LC_MESSAGES/django.mo
pretix_stay22/locale/ru/LC_MESSAGES/django.po
pretix_stay22/locale/si/LC_MESSAGES/django.mo
pretix_stay22/locale/si/LC_MESSAGES/django.po
pretix_stay22/locale/sk/LC_MESSAGES/django.mo
pretix_stay22/locale/sk/LC_MESSAGES/django.po
pretix_stay22/locale/uk/LC_MESSAGES/django.mo
pretix_stay22/locale/uk/LC_MESSAGES/django.po
pretix_stay22/locale/zh_Hans/LC_MESSAGES/django.mo
pretix_stay22/locale/zh_Hans/LC_MESSAGES/django.po
pretix_stay22/static/pretix_stay22/.gitkeep
pretix_stay22/static/pretix_stay22/logo.svg
pretix_stay22-1.3.0.dist-info/LICENSE
pretix_stay22-1.3.0.dist-info/METADATA
pretix_stay22-1.3.0.dist-info/WHEEL
pretix_stay22-1.3.0.dist-info/entry_points.txt
pretix_stay22-1.3.0.dist-info/top_level.txt
pretix_stay22-1.3.0.dist-info/RECORD
