Metadata-Version: 2.1
Name: pretix-stay22
Version: 1.3.0
Summary: This plugin allows to integrate the Stay22 hotel map into your pretix shop
Author-email: pretix team <support@pretix.eu>
Maintainer-email: pretix team <support@pretix.eu>
License: 
Project-URL: homepage, https://github.com/pretix/pretix-stay22
Keywords: pretix
Requires-Python: >=3.9
License-File: LICENSE
